jaehyeokTest/test1.py
jaehyeokTest/test2.py
jaehyeokTest-0.0.0.2.dist-info/METADATA
jaehyeokTest-0.0.0.2.dist-info/WHEEL
jaehyeokTest-0.0.0.2.dist-info/top_level.txt
jaehyeokTest-0.0.0.2.dist-info/RECORD
