Metadata-Version: 2.1
Name: jaehyeokTest
Version: 0.0.0.2
Summary: My First Test Package
Home-page: https://lingua.blog.me/...
Author: JaeHyeok Lee
Author-email: jhcr7@naver.com
License: MIT
Platform: UNKNOWN
Requires-Python: >=3
